<!DOCTYPE suite SYSTEM "http://testng.org/testng-1.0.dtd" > 

<suite name="Flynas" allow-return-values="true" verbose="2">
    
    
	<test name="IBE-UAT-Regression" >
	    
	   	<!--	<groups>
				<run>
					<include name="chrome"/>
				</run>
			</groups> -->
		  
			<classes>	 	
					<!-- ********************************Total - 18*************************************************** -->
					
					
						
						<class name="flynas.web.uat.regression.TC35_AnonymousOneWayDomesticEconomy_MMB_ModifyExtrasSeat"/>
						<class name="flynas.web.uat.regression.TC35_b_AnonymousOwIntlEconomy_MMB_ModifyExtrasSeat"/>
					
						<class name="flynas.web.uat.regression.TC45_oneWayDomCancelverifyMMB"/>
								
		 
		</classes>
	</test>
	
	

</suite>